{"name":"Angular-form-validation","tagline":"angular form validation","body":"# angular-form-validation\r\n\r\nThis plugin can be used to show validation message.\r\n\r\n## Directives\r\n* `form-validation` : This can be used with form tag. It initiate the form validations and show the validation messages on form submit if validation fails\r\n* `validation-message` : This can be used to register a field with validation and validation message/code\r\n* `form-error` : This can be used to show validation message, act as a placeholder in DOM, can be placed inside form or outside form.\r\n\r\n","google":"","note":"Don't delete this file! It's used internally to help with page regeneration."}